cn2date/__init__.py
cn2date/chine_date.lark
cn2date/cn2date.py
cn2date/cn2date_test.py
cn2date/conf.py
cn2date/datetime.py
cn2date/norm_date.lark
cn2date/transform.py
cn2date/__pycache__/__init__.cpython-310.pyc
cn2date/__pycache__/cn2date.cpython-310.pyc
cn2date/__pycache__/cn2date_test.cpython-310.pyc
cn2date/__pycache__/conf.cpython-310.pyc
cn2date/__pycache__/datetime.cpython-310.pyc
cn2date/__pycache__/transform.cpython-310.pyc
cn2date-0.1.2.dist-info/LICENSE
cn2date-0.1.2.dist-info/METADATA
cn2date-0.1.2.dist-info/WHEEL
cn2date-0.1.2.dist-info/top_level.txt
cn2date-0.1.2.dist-info/RECORD
