Metadata-Version: 2.2
Name: cn2date
Version: 0.1.2
Summary: 中文日期 、口语 转换为 日期字符串
Home-page: https://github.com/drawmoon/cn2date
Author: drash
Author-email: drawmoonsh@outlook.com.com
License: MIT License
Classifier: Programming Language :: Python :: 3.9
Classifier: License :: OSI Approved :: MIT License
Classifier: Operating System :: OS Independent
Requires-Python: >=3.9
License-File: LICENSE
Requires-Dist: lark
Requires-Dist: python-dateutil
Requires-Dist: cn2an
Dynamic: author
Dynamic: author-email
Dynamic: classifier
Dynamic: description
Dynamic: description-content-type
Dynamic: home-page
Dynamic: license
Dynamic: requires-dist
Dynamic: requires-python
Dynamic: summary
